faceted/__init__.py
faceted/_version.py
faceted/faceted.py
faceted/tests/__init__.py
faceted/tests/test_faceted.py
faceted-0.2.1.dist-info/LICENSE
faceted-0.2.1.dist-info/METADATA
faceted-0.2.1.dist-info/WHEEL
faceted-0.2.1.dist-info/top_level.txt
faceted-0.2.1.dist-info/RECORD
