Metadata-Version: 2.1
Name: faceted
Version: 0.2.1
Summary: Precisely spaced subplots
Home-page: https://github.com/spencerkclark/faceted
Author: Spencer K. Clark
Author-email: spencerkclark@gmail.com
License: UNKNOWN
Keywords: matplotlib cartopy multi-panel plots colorbars
Platform: UNKNOWN
Classifier: Development Status :: 4 - Beta
Classifier: Intended Audience :: Science/Research
Classifier: License :: OSI Approved :: MIT License
Classifier: Natural Language :: English
Classifier: Operating System :: OS Independent
Classifier: Programming Language :: Python :: 3
Classifier: Programming Language :: Python :: 3.5
Classifier: Programming Language :: Python :: 3.6
Classifier: Programming Language :: Python :: 3.7
Classifier: Topic :: Scientific/Engineering
License-File: LICENSE
Requires-Dist: matplotlib (>=1.5)
Requires-Dist: numpy (>=1.7)
